__init__.py
main.py
segment.py
test.py
train.py
webcam.py
checkpoints/__init__.py
checkpoints/best.pth
config/__init__.py
config/config.py
data/__init__.py
data/dataloader.py
data/test_loader.py
data/utils.py
haircosys/__init__.py
haircosys/jo.py
haircosys/predict.py
loss/__init__.py
loss/loss.py
models/__init__.py
models/blocks.py
models/modelv1.py
models/modelv2.py
models/quantization/__init__.py
models/quantization/blocks.py
models/quantization/modelv1.py
models/quantization/modelv2.py
requirements/__init__.py
requirements/requirements.txt
requirements/test_requirements.txt
utils/__init__.py
utils/custom_transfrom.py
utils/util.py
HairSys-0.0.12.dist-info/LICENSE
HairSys-0.0.12.dist-info/METADATA
HairSys-0.0.12.dist-info/WHEEL
HairSys-0.0.12.dist-info/top_level.txt
HairSys-0.0.12.dist-info/RECORD
